polywhirl/__init__.py
polywhirl/__main__.py
polywhirl-0.1.0.dist-info/LICENSE
polywhirl-0.1.0.dist-info/METADATA
polywhirl-0.1.0.dist-info/WHEEL
polywhirl-0.1.0.dist-info/entry_points.txt
polywhirl-0.1.0.dist-info/top_level.txt
polywhirl-0.1.0.dist-info/RECORD
