Metadata-Version: 2.1
Name: polywhirl
Version: 0.1.0
Summary: Run pandas-profiling HTML reports for a given list of database tables.
Home-page: https://github.com/asdfgeoff/polywhirl
License: MIT
Platform: UNKNOWN
Classifier: License :: OSI Approved :: MIT License
Classifier: Programming Language :: Python
Classifier: Programming Language :: Python :: 3
Classifier: Programming Language :: Python :: 3.6
Requires-Python: >=3.6.0
Requires-Dist: pandas
Requires-Dist: pandas-profiling
Requires-Dist: pandas-gbq
Requires-Dist: PyYAML
Requires-Dist: tqdm
Requires-Dist: jinja2
Requires-Dist: click
